codehash/__init__.py
codehash-0.1.0.dist-info/LICENSE
codehash-0.1.0.dist-info/WHEEL
codehash-0.1.0.dist-info/METADATA
codehash-0.1.0.dist-info/RECORD
