Metadata-Version: 2.1
Name: codehash
Version: 0.1.0
Summary: Hashing Python code
Home-page: https://github.com/jhrmnn/codehash
License: MPL-2.0
Author: Jan Hermann
Author-email: dev@jan.hermann.name
Requires-Python: >=3.7,<4.0
Classifier: Development Status :: 4 - Beta
Classifier: Intended Audience :: Developers
Classifier: License :: OSI Approved
Classifier: Programming Language :: Python :: 3
Classifier: Programming Language :: Python :: 3.7
Classifier: Programming Language :: Python :: 3.8
Classifier: Programming Language :: Python :: 3.9
Classifier: Topic :: Utilities
Requires-Dist: typing_extensions (>=3.6,<4.0)
Project-URL: Documentation, https://jhrmnn.github.io/codehash
Project-URL: Repository, https://github.com/jhrmnn/codehash
